lemmings/__init__.py
lemmings/executor.py
lemmings/rps.py
lemmings/setup.py
lemmings/shared.py
lemmings/statistics.py
lemmings/task.py
lemmings/task_set.py
lemmings/task_set_run.py
lemmings/worker.py
lemmings/utils/__init__.py
lemmings/utils/colors.py
lemmings/utils/const.py
lemmings/utils/coroutine.py
lemmings/utils/influx.py
lemmings/utils/metrics.py
lemmings/utils/parsing.py
lemmings/utils/prometheus.py
lemmings/utils/timer.py
lemmings/utils/timer_prom.py
lemmings/utils/utils.py
lemmings-0.10.0.dist-info/LICENSE
lemmings-0.10.0.dist-info/METADATA
lemmings-0.10.0.dist-info/WHEEL
lemmings-0.10.0.dist-info/top_level.txt
lemmings-0.10.0.dist-info/RECORD
