Metadata-Version: 2.1
Name: lemmings
Version: 0.10.0
Summary: Async load testing framework
Home-page: https://bitbucket.org/radiantgeek/lemmings
Author: radiantgeek
Author-email: 
License: MIT
Platform: UNKNOWN
Classifier: Programming Language :: Python :: 3
Classifier: License :: OSI Approved :: MIT License
Classifier: Operating System :: OS Independent
Requires-Python: >=3.7
Requires-Dist: httpx (>=0.11.1)
Requires-Dist: psutil (>=5.7.0)
Requires-Dist: prometheus-client (>=0.7.1)
